archimedean/__init__.py
archimedean-5.9.data/scripts/archimedean
bin/__init__.py
bin/dadeschools.py
archimedean-5.9.dist-info/METADATA
archimedean-5.9.dist-info/WHEEL
archimedean-5.9.dist-info/top_level.txt
archimedean-5.9.dist-info/RECORD
