Metadata-Version: 2.1
Name: archimedean
Version: 5.9
Summary: The Ultimate Archimedean CLI
Author: Daniel Li
Author-email: daniel.miami2005@gmail.com
Classifier: Programming Language :: Python :: 3
Classifier: License :: OSI Approved :: MIT License
Classifier: Operating System :: OS Independent
Requires-Python: >=3.6
Requires-Dist: click
Requires-Dist: requests
Requires-Dist: bs4
Requires-Dist: python-dotenv
